StreetFightingMathematicsLectureNotesMit6009/README.md
StreetFightingMathematicsLectureNotesMit6009/__init__.py
StreetFightingMathematicsLectureNotesMit6009/__main__.py
StreetFightingMathematicsLectureNotesMit6009/file.pdf
StreetFightingMathematicsLectureNotesMit6009/index.html
street_fighting_mathematics_lecture_notes_mit_6_009-2024.3.2.0.dist-info/METADATA
street_fighting_mathematics_lecture_notes_mit_6_009-2024.3.2.0.dist-info/WHEEL
street_fighting_mathematics_lecture_notes_mit_6_009-2024.3.2.0.dist-info/entry_points.txt
street_fighting_mathematics_lecture_notes_mit_6_009-2024.3.2.0.dist-info/top_level.txt
street_fighting_mathematics_lecture_notes_mit_6_009-2024.3.2.0.dist-info/RECORD
